{
  "headers": {
    "x-content-type-options": "nosniff",
    "content-type": "application/typescript; charset=utf-8",
    "cross-origin-opener-policy": "same-origin",
    "date": "Thu, 16 May 2024 07:18:18 GMT",
    "access-control-allow-origin": "*",
    "etag": "\"601af9b27645fa551c1b59a632dfd07d\"",
    "strict-transport-security": "max-age=63072000; includeSubDomains; preload",
    "via": "http/2 edgeproxy-h",
    "x-amz-cf-id": "29Y4VgCr1xPtVuuHlcu5U3KLVagpfT3Ak3E9f2YPmkLnnbNZu_OJfg==",
    "x-frame-options": "DENY",
    "x-amz-version-id": "qbsccDw6Nc2QbHQa_zSTId1.MK6pko3_",
    "referrer-policy": "strict-origin-when-cross-origin",
    "x-cache": "Hit from cloudfront",
    "last-modified": "Fri, 25 Mar 2022 13:32:50 GMT",
    "accept-ranges": "bytes",
    "cache-control": "public, max-age=31536000, immutable",
    "content-security-policy": "default-src 'none'; style-src 'unsafe-inline'; sandbox",
    "server-timing": "fetchSource;dur=6",
    "content-length": "2836",
    "vary": "Accept-Encoding, Origin",
    "cross-origin-embedder-policy": "same-origin",
    "cross-origin-resource-policy": "same-origin",
    "age": "14611016",
    "server": "deno/gcp-europe-west3",
    "x-amz-cf-pop": "FRA56-P5",
    "x-amz-replication-status": "COMPLETED"
  },
  "url": "https://deno.land/std@0.132.0/node/internal/querystring.ts",
  "now": {
    "secs_since_epoch": 1730454913,
    "nanos_since_epoch": 575798670
  }
}